README.md
setup.py
jx_elasticsearch/__init__.py
jx_elasticsearch/elasticsearch.py
jx_elasticsearch/meta.py
jx_elasticsearch/meta_columns.py
jx_elasticsearch/rollover_index.py
jx_elasticsearch/typed_inserter.py
jx_elasticsearch.egg-info/PKG-INFO
jx_elasticsearch.egg-info/SOURCES.txt
jx_elasticsearch.egg-info/dependency_links.txt
jx_elasticsearch.egg-info/not-zip-safe
jx_elasticsearch.egg-info/requires.txt
jx_elasticsearch.egg-info/top_level.txt
jx_elasticsearch/es52/__init__.py
jx_elasticsearch/es52/agg_bulk.py
jx_elasticsearch/es52/agg_format.py
jx_elasticsearch/es52/agg_op.py
jx_elasticsearch/es52/agg_op_field.py
jx_elasticsearch/es52/agg_op_formula.py
jx_elasticsearch/es52/decoders.py
jx_elasticsearch/es52/es_query.py
jx_elasticsearch/es52/set_bulk.py
jx_elasticsearch/es52/set_format.py
jx_elasticsearch/es52/set_op.py
jx_elasticsearch/es52/stats.py
jx_elasticsearch/es52/util.py
jx_elasticsearch/es52/expressions/__init__.py
jx_elasticsearch/es52/expressions/and_op.py
jx_elasticsearch/es52/expressions/basic_eq_op.py
jx_elasticsearch/es52/expressions/basic_starts_with_op.py
jx_elasticsearch/es52/expressions/boolean_op.py
jx_elasticsearch/es52/expressions/case_op.py
jx_elasticsearch/es52/expressions/coalesce_op.py
jx_elasticsearch/es52/expressions/concat_op.py
jx_elasticsearch/es52/expressions/div_op.py
jx_elasticsearch/es52/expressions/eq_op.py
jx_elasticsearch/es52/expressions/es_select_op.py
jx_elasticsearch/es52/expressions/exists_op.py
jx_elasticsearch/es52/expressions/false_op.py
jx_elasticsearch/es52/expressions/find_op.py
jx_elasticsearch/es52/expressions/gt_op.py
jx_elasticsearch/es52/expressions/gte_op.py
jx_elasticsearch/es52/expressions/in_op.py
jx_elasticsearch/es52/expressions/inner_join_op.py
jx_elasticsearch/es52/expressions/length_op.py
jx_elasticsearch/es52/expressions/literal.py
jx_elasticsearch/es52/expressions/lt_op.py
jx_elasticsearch/es52/expressions/lte_op.py
jx_elasticsearch/es52/expressions/missing_op.py
jx_elasticsearch/es52/expressions/ne_op.py
jx_elasticsearch/es52/expressions/nested_op.py
jx_elasticsearch/es52/expressions/not_op.py
jx_elasticsearch/es52/expressions/or_op.py
jx_elasticsearch/es52/expressions/outer_join_op.py
jx_elasticsearch/es52/expressions/prefix_op.py
