Metadata-Version: 2.1
Name: jx-elasticsearch
Version: 3.99.20292
Summary: JSON query expressions for Elasticsearch
Home-page: https://github.com/klahnakoski/jx-elasticsearch
Author: Kyle Lahnakoski
Author-email: kyle@lahnakoski.com
License: MPL 2.0
Platform: UNKNOWN
Classifier: Development Status :: 4 - Beta
Classifier: Topic :: Software Development :: Libraries
Classifier: Topic :: Software Development :: Libraries :: Python Modules
Classifier: License :: OSI Approved :: Mozilla Public License 2.0 (MPL 2.0)
Classifier: Programming Language :: Python :: 2.7
Classifier: Programming Language :: Python :: 3.6
